db_libs/__init__.py
db_libs/mongo_fork_safe.py
db_libs/mongo_lib.py
db_libs/mysql_lib.py
db_libs/redis_lib.py
db_libs/sqla_lib.py
db_libs-0.8.dist-info/METADATA
db_libs-0.8.dist-info/WHEEL
db_libs-0.8.dist-info/top_level.txt
db_libs-0.8.dist-info/RECORD
