Metadata-Version: 2.1
Name: db-libs
Version: 0.8
Summary: 'redis', 'mongo', 'elasticsearch', 'mysql', 'sqlachemy', '线程安全的数据库封装，享元模式支持无限实例化调用'
Home-page: 
Author: bfzs
Author-email: ydf0509@sohu.com
Maintainer: ydf
Maintainer-email: ydf0509@sohu.com
License: BSD License
Keywords: database,redis,mongo,elasticsearch,mysql,sqlachemy
Platform: all
Classifier: Development Status :: 4 - Beta
Classifier: Operating System :: OS Independent
Classifier: Intended Audience :: Developers
Classifier: License :: OSI Approved :: BSD License
Classifier: Programming Language :: Python
Classifier: Programming Language :: Python :: Implementation
Classifier: Programming Language :: Python :: 3.6
Classifier: Topic :: Software Development :: Libraries
Requires-Dist: nb-log
Requires-Dist: decorator-libs
Requires-Dist: redis
Requires-Dist: pymongo
Requires-Dist: elasticsearch
Requires-Dist: threadpool-executor-shrink-able
Requires-Dist: redis2
Requires-Dist: redis3
Requires-Dist: pymysql
Requires-Dist: records
